Metadata-Version: 2.0
Name: spire
Version: 0.4.2
Summary: Simple Prototyping for Image Reconstruction
Home-page: https://github.com/pierrepaleo/spire
Author: Pierre Paleo
Author-email: pierre.paleo@esrf.fr
License: BSD
Platform: linux_x86
Platform: linux_x86_64
